gradescopeapi/__init__.py
gradescopeapi/py.typed
gradescopeapi/_config/__init__.py
gradescopeapi/_config/config.py
gradescopeapi/api/__init__.py
gradescopeapi/api/api.py
gradescopeapi/api/constants.py
gradescopeapi/classes/__init__.py
gradescopeapi/classes/account.py
gradescopeapi/classes/assignments.py
gradescopeapi/classes/connection.py
gradescopeapi/classes/courses.py
gradescopeapi/classes/extensions.py
gradescopeapi/classes/member.py
gradescopeapi/classes/submission.py
gradescopeapi/classes/upload.py
gradescopeapi/classes/_helpers/_assignment_helpers.py
gradescopeapi/classes/_helpers/_course_helpers.py
gradescopeapi/classes/_helpers/_login_helpers.py
gradescopeapi-1.7.0.dist-info/METADATA
gradescopeapi-1.7.0.dist-info/WHEEL
gradescopeapi-1.7.0.dist-info/licenses/LICENSE.md
gradescopeapi-1.7.0.dist-info/RECORD
