Metadata-Version: 2.4
Name: gradescopeapi
Version: 1.7.0
Summary: Library for programmatically interacting with Gradescope.
Project-URL: Homepage, https://github.com/nyuoss/gradescope-api
Project-URL: Issues, https://github.com/nyuoss/gradescope-api/issues
Project-URL: Repository, https://github.com/nyuoss/gradescope-api
Author: Berry Liu, Calvin Tian, Kevin Zheng, Margaret Jagger, Susmitha Kusuma
Maintainer: Calvin Tian
License: MIT
License-File: LICENSE.md
Classifier: Programming Language :: Python :: 3 :: Only
Classifier: Programming Language :: Python :: 3.10
Classifier: Programming Language :: Python :: 3.11
Classifier: Programming Language :: Python :: 3.12
Classifier: Programming Language :: Python :: 3.13
Requires-Python: >=3.10
Requires-Dist: beautifulsoup4>=4.12.3
Requires-Dist: fastapi>=0.111.0
Requires-Dist: pytest>=8.2.0
Requires-Dist: python-dateutil>=2.9.0.post0
Requires-Dist: python-dotenv>=1.0.1
Requires-Dist: requests-toolbelt>=1.0.0
Requires-Dist: requests>=2.31.0
Requires-Dist: tzdata>=2024.2
